array_typing/__init__.py
array_typing/__init__.pyi
array_typing/py.typed
array_typing/array_like/__init__.py
array_typing/array_like/__init__.pyi
array_typing/array_like/_bool.py
array_typing/array_like/_export.py
array_typing/array_like/_float.py
array_typing/array_like/_integer.py
array_typing/array_like/_types.py
array_typing/array_like/_utils.py
array_typing/jax/__init__.py
array_typing/jax/__init__.pyi
array_typing/jax/_bool.py
array_typing/jax/_export.py
array_typing/jax/_float.py
array_typing/jax/_integer.py
array_typing/jax/_utils.py
array_typing/numpy/__init__.py
array_typing/numpy/__init__.pyi
array_typing/numpy/_bool.py
array_typing/numpy/_export.py
array_typing/numpy/_float.py
array_typing/numpy/_integer.py
array_typing/numpy/_utils/__init__.py
array_typing/numpy/_utils/__init__.pyi
array_typing/numpy/_utils/_as_dtype.py
array_typing/numpy/_utils/_as_numpy.py
array_typing/numpy/_utils/_is.py
array_typing/numpy/_utils/_scale.py
array_typing/python/__init__.py
array_typing/python/__init__.pyi
array_typing/python/_cast.py
array_typing/torch/__init__.py
array_typing/torch/__init__.pyi
array_typing/torch/_bool.py
array_typing/torch/_export.py
array_typing/torch/_float.py
array_typing/torch/_integer.py
array_typing/torch/_utils.py
array_typing/typing/__init__.py
array_typing/typing/__init__.pyi
array_typing/typing/_is.py
array_typing/typing/_name.py
array_typing/typing/_types.py
array_typing/utils/__init__.py
array_typing/utils/__init__.pyi
array_typing/utils/_sequence.py
array_typing-0.0.0.dist-info/METADATA
array_typing-0.0.0.dist-info/WHEEL
array_typing-0.0.0.dist-info/licenses/LICENSE
array_typing-0.0.0.dist-info/RECORD
