Metadata-Version: 2.3
Name: array-typing
Version: 0.0.0
Summary: Add your description here
Author-email: liblaf <30631553+liblaf@users.noreply.github.com>
Requires-Python: >=3.11
Requires-Dist: beartype>=0.19.0
Requires-Dist: jaxtyping>=0.2.36
Requires-Dist: lazy-loader>=0.4
Requires-Dist: numpy>=2.1.3
Provides-Extra: jax
Requires-Dist: jax>=0.4.35; extra == 'jax'
Provides-Extra: torch
Requires-Dist: torch>=2.5.1; extra == 'torch'
